odoo/addons/mrp_production_generator_by_date_interval/README.rst
odoo/addons/mrp_production_generator_by_date_interval/__init__.py
odoo/addons/mrp_production_generator_by_date_interval/__manifest__.py
odoo/addons/mrp_production_generator_by_date_interval/i18n/es.po
odoo/addons/mrp_production_generator_by_date_interval/i18n/it.po
odoo/addons/mrp_production_generator_by_date_interval/i18n/mrp_production_generator_by_date_interval.pot
odoo/addons/mrp_production_generator_by_date_interval/readme/CONTRIBUTORS.md
odoo/addons/mrp_production_generator_by_date_interval/readme/DESCRIPTION.md
odoo/addons/mrp_production_generator_by_date_interval/readme/ROADMAP.md
odoo/addons/mrp_production_generator_by_date_interval/readme/USAGE.md
odoo/addons/mrp_production_generator_by_date_interval/security/ir.model.access.csv
odoo/addons/mrp_production_generator_by_date_interval/static/description/icon.png
odoo/addons/mrp_production_generator_by_date_interval/static/description/index.html
odoo/addons/mrp_production_generator_by_date_interval/tests/__init__.py
odoo/addons/mrp_production_generator_by_date_interval/tests/test_mrp_production_generator.py
odoo/addons/mrp_production_generator_by_date_interval/wizards/__init__.py
odoo/addons/mrp_production_generator_by_date_interval/wizards/mrp_production_generator_date_interval_wizard.py
odoo/addons/mrp_production_generator_by_date_interval/wizards/mrp_production_generator_date_interval_wizard_views.xml
odoo_addon_mrp_production_generator_by_date_interval-17.0.1.0.0.4.dist-info/METADATA
odoo_addon_mrp_production_generator_by_date_interval-17.0.1.0.0.4.dist-info/WHEEL
odoo_addon_mrp_production_generator_by_date_interval-17.0.1.0.0.4.dist-info/top_level.txt
odoo_addon_mrp_production_generator_by_date_interval-17.0.1.0.0.4.dist-info/RECORD
